mbox2eml.py
mbox2eml-0.1.2.dist-info/METADATA
mbox2eml-0.1.2.dist-info/WHEEL
mbox2eml-0.1.2.dist-info/RECORD
