Metadata-Version: 2.3
Name: mbox2eml
Version: 0.1.2
Summary: Convert Mbox to EML Files Easily
Author: Yangwook Jeong
Author-email: yangwookee@gmail.com
Requires-Python: >=3.11,<4.0
Classifier: Programming Language :: Python :: 3
Classifier: Programming Language :: Python :: 3.11
Classifier: Programming Language :: Python :: 3.12
Classifier: Programming Language :: Python :: 3.13
Requires-Dist: taskipy (>=1.14.1,<2.0.0)
Requires-Dist: tqdm (>=4.67.1,<5.0.0)
